hypercurrentdjango/__init__.py
hypercurrentdjango/middleware.py
hypercurrent_django-1.0.5.dist-info/LICENSE
hypercurrent_django-1.0.5.dist-info/METADATA
hypercurrent_django-1.0.5.dist-info/WHEEL
hypercurrent_django-1.0.5.dist-info/top_level.txt
hypercurrent_django-1.0.5.dist-info/RECORD
