Metadata-Version: 2.1
Name: hypercurrent-django
Version: 1.0.5
Summary: HyperCurrent Middleware for Python Django
Home-page: https://github.com/hypercurrentio/hypercurrentdjango
Author: HyperCurrent, Inc
Author-email: info@hypercurrent.io
License: Apache Software License
Classifier: Framework :: Django
Classifier: Programming Language :: Python :: 3
License-File: LICENSE
Requires-Dist: Django >=3.0
Requires-Dist: hypercurrent-metering
